package/__init__.py
package/covid_data_handler.py
package/covid_news_handling.py
package/covid_user_interface.py
pkg_luishidalgogt2003-0.0.1.dist-info/LICENSE.txt
pkg_luishidalgogt2003-0.0.1.dist-info/METADATA
pkg_luishidalgogt2003-0.0.1.dist-info/WHEEL
pkg_luishidalgogt2003-0.0.1.dist-info/top_level.txt
pkg_luishidalgogt2003-0.0.1.dist-info/RECORD
