Metadata-Version: 2.1
Name: pkg-luishidalgogt2003
Version: 0.0.1
Summary: A small package
Home-page: https://github.com/pypa/sampleproject
Author: Luis Hidalgo Gutierrez De Tovar 
Author-email: luigihg592@gmail.com
License: UNKNOWN
Project-URL: Bug Tracker, https://github.com/pypa/sampleproject/issues
Platform: UNKNOWN
Classifier: Programming Language :: Python :: 3
Classifier: License :: OSI Approved :: MIT License
Classifier: Operating System :: OS Independent
Requires-Python: >=3.6
License-File: LICENSE.txt
